yasmine_cli/__init__.py
yasmine_cli/config.yml
yasmine_cli/yasmine_cli.py
yasmine_cli/fdsn-schema/fdsn-station-1.0.xsd
yasmine_cli/fdsn-schema/fdsn-station-1.1.xsd
yasmine_cli/libs/__init__.py
yasmine_cli/libs/edit_xml_to_inv.py
yasmine_cli/libs/libs_log.py
yasmine_cli/libs/libs_obs.py
yasmine_cli/libs/libs_util.py
yasmine_cli/libs/libs_xml.py
yasmine_cli/libs/plot_poly_resp.py
yasmine_cli/yml/channel.yml
yasmine_cli/yml/comment.yml
yasmine_cli/yml/comments.yml
yasmine_cli/yml/dataavailability.yml
yasmine_cli/yml/equipment.yml
yasmine_cli/yml/equipments.yml
yasmine_cli/yml/externalreference.yml
yasmine_cli/yml/identifiers.yml
yasmine_cli/yml/network.yml
yasmine_cli/yml/networkYP.yml
yasmine_cli/yml/operator.yml
yasmine_cli/yml/operator.yml.bup
yasmine_cli/yml/operator2.yml
yasmine_cli/yml/operators.yml
yasmine_cli/yml/reference.yml
yasmine_cli/yml/sensor.sts2.yml
yasmine_cli/yml/sensor.yml
yasmine_cli/yml/sensor.yml.sts2
yasmine_cli/yml/sensor_PF.yml
yasmine_cli/yml/site.yml
yasmine_cli/yml/station.yml
yasmine_cli/yml/update.yml
yasmine_cli-0.0.6.data/data/lib/python3.8/site-packages/yasmine_cli/fdsn-schema/fdsn-station-1.0.xsd
yasmine_cli-0.0.6.data/data/lib/python3.8/site-packages/yasmine_cli/fdsn-schema/fdsn-station-1.1.xsd
yasmine_cli-0.0.6.dist-info/AUTHORS.rst
yasmine_cli-0.0.6.dist-info/LICENSE
yasmine_cli-0.0.6.dist-info/METADATA
yasmine_cli-0.0.6.dist-info/WHEEL
yasmine_cli-0.0.6.dist-info/entry_points.txt
yasmine_cli-0.0.6.dist-info/top_level.txt
yasmine_cli-0.0.6.dist-info/RECORD
